[{"model": "dashboard.season", "pk": 1, "fields": {"number": 1, "start_date": "2024-01-28T00:00:00Z", "end_date": "2024-03-16T23:59:59Z"}}, {"model": "dashboard.team", "pk": 1, "fields": {"name": "Gaspard", "seasons": [1]}}, {"model": "dashboard.team", "pk": 2, "fields": {"name": "FC Ghostibusti", "seasons": [1]}}, {"model": "dashboard.team", "pk": 3, "fields": {"name": "Lazio de Rhum", "seasons": [1]}}, {"model": "dashboard.team", "pk": 4, "fields": {"name": "Magic Team", "seasons": [1]}}, {"model": "dashboard.team", "pk": 5, "fields": {"name": "Boucherie Française", "seasons": [1]}}, {"model": "dashboard.team", "pk": 6, "fields": {"name": "off", "seasons": [1]}}, {"model": "dashboard.team", "pk": 7, "fields": {"name": "Les Galaktiks", "seasons": [1]}}, {"model": "dashboard.team", "pk": 8, "fields": {"name": "Inter de Lille", "seasons": [1]}}, {"model": "dashboard.game", "pk": 57, "fields": {"season": 1, "matchday": 5, "team_one": 8, "team_two": 4, "referee_team": null, "team_one_home_goals": null, "team_one_away_goals": null, "team_two_home_goals": null, "team_two_away_goals": null, "agreed": null, "home_goals": null, "away_goals": null}}, {"model": "dashboard.game", "pk": 58, "fields": {"season": 1, "matchday": 5, "team_one": 2, "team_two": 7, "referee_team": null, "team_one_home_goals": null, "team_one_away_goals": null, "team_two_home_goals": null, "team_two_away_goals": null, "agreed": null, "home_goals": null, "away_goals": null}}, {"model": "dashboard.game", "pk": 59, "fields": {"season": 1, "matchday": 5, "team_one": 1, "team_two": 5, "referee_team": 1, "team_one_home_goals": null, "team_one_away_goals": null, "team_two_home_goals": null, "team_two_away_goals": null, "agreed": null, "home_goals": null, "away_goals": null}}, {"model": "dashboard.game", "pk": 60, "fields": {"season": 1, "matchday": 5, "team_one": 6, "team_two": 3, "referee_team": null, "team_one_home_goals": null, "team_one_away_goals": null, "team_two_home_goals": null, "team_two_away_goals": null, "agreed": null, "home_goals": null, "away_goals": null}}, {"model": "dashboard.game", "pk": 61, "fields": {"season": 1, "matchday": 2, "team_one": 4, "team_two": 2, "referee_team": null, "team_one_home_goals": null, "team_one_away_goals": null, "team_two_home_goals": null, "team_two_away_goals": null, "agreed": null, "home_goals": null, "away_goals": null}}, {"model": "dashboard.game", "pk": 62, "fields": {"season": 1, "matchday": 2, "team_one": 8, "team_two": 5, "referee_team": null, "team_one_home_goals": null, "team_one_away_goals": null, "team_two_home_goals": null, "team_two_away_goals": null, "agreed": null, "home_goals": null, "away_goals": null}}, {"model": "dashboard.game", "pk": 63, "fields": {"season": 1, "matchday": 2, "team_one": 6, "team_two": 7, "referee_team": null, "team_one_home_goals": null, "team_one_away_goals": null, "team_two_home_goals": null, "team_two_away_goals": null, "agreed": null, "home_goals": null, "away_goals": null}}, {"model": "dashboard.game", "pk": 64, "fields": {"season": 1, "matchday": 2, "team_one": 3, "team_two": 1, "referee_team": null, "team_one_home_goals": null, "team_one_away_goals": null, "team_two_home_goals": null, "team_two_away_goals": null, "agreed": null, "home_goals": null, "away_goals": null}}, {"model": "dashboard.game", "pk": 65, "fields": {"season": 1, "matchday": 3, "team_one": 5, "team_two": 4, "referee_team": null, "team_one_home_goals": null, "team_one_away_goals": null, "team_two_home_goals": null, "team_two_away_goals": null, "agreed": null, "home_goals": null, "away_goals": null}}, {"model": "dashboard.game", "pk": 66, "fields": {"season": 1, "matchday": 3, "team_one": 6, "team_two": 2, "referee_team": null, "team_one_home_goals": null, "team_one_away_goals": null, "team_two_home_goals": null, "team_two_away_goals": null, "agreed": null, "home_goals": null, "away_goals": null}}, {"model": "dashboard.game", "pk": 67, "fields": {"season": 1, "matchday": 3, "team_one": 8, "team_two": 3, "referee_team": null, "team_one_home_goals": null, "team_one_away_goals": null, "team_two_home_goals": null, "team_two_away_goals": null, "agreed": null, "home_goals": null, "away_goals": null}}, {"model": "dashboard.game", "pk": 68, "fields": {"season": 1, "matchday": 3, "team_one": 1, "team_two": 7, "referee_team": null, "team_one_home_goals": null, "team_one_away_goals": null, "team_two_home_goals": null, "team_two_away_goals": null, "agreed": null, "home_goals": null, "away_goals": null}}, {"model": "dashboard.game", "pk": 69, "fields": {"season": 1, "matchday": 4, "team_one": 4, "team_two": 6, "referee_team": null, "team_one_home_goals": null, "team_one_away_goals": null, "team_two_home_goals": null, "team_two_away_goals": null, "agreed": null, "home_goals": null, "away_goals": null}}, {"model": "dashboard.game", "pk": 70, "fields": {"season": 1, "matchday": 4, "team_one": 5, "team_two": 3, "referee_team": null, "team_one_home_goals": null, "team_one_away_goals": null, "team_two_home_goals": null, "team_two_away_goals": null, "agreed": null, "home_goals": null, "away_goals": null}}, {"model": "dashboard.game", "pk": 71, "fields": {"season": 1, "matchday": 4, "team_one": 2, "team_two": 1, "referee_team": null, "team_one_home_goals": null, "team_one_away_goals": null, "team_two_home_goals": null, "team_two_away_goals": null, "agreed": null, "home_goals": null, "away_goals": null}}, {"model": "dashboard.game", "pk": 72, "fields": {"season": 1, "matchday": 4, "team_one": 8, "team_two": 7, "referee_team": null, "team_one_home_goals": null, "team_one_away_goals": null, "team_two_home_goals": null, "team_two_away_goals": null, "agreed": null, "home_goals": null, "away_goals": null}}, {"model": "dashboard.game", "pk": 73, "fields": {"season": 1, "matchday": 1, "team_one": 3, "team_two": 4, "referee_team": null, "team_one_home_goals": null, "team_one_away_goals": null, "team_two_home_goals": null, "team_two_away_goals": null, "agreed": null, "home_goals": null, "away_goals": null}}, {"model": "dashboard.game", "pk": 74, "fields": {"season": 1, "matchday": 1, "team_one": 1, "team_two": 6, "referee_team": null, "team_one_home_goals": null, "team_one_away_goals": null, "team_two_home_goals": null, "team_two_away_goals": null, "agreed": null, "home_goals": null, "away_goals": null}}, {"model": "dashboard.game", "pk": 75, "fields": {"season": 1, "matchday": 1, "team_one": 5, "team_two": 7, "referee_team": null, "team_one_home_goals": null, "team_one_away_goals": null, "team_two_home_goals": null, "team_two_away_goals": null, "agreed": null, "home_goals": null, "away_goals": null}}, {"model": "dashboard.game", "pk": 76, "fields": {"season": 1, "matchday": 1, "team_one": 2, "team_two": 8, "referee_team": null, "team_one_home_goals": null, "team_one_away_goals": null, "team_two_home_goals": null, "team_two_away_goals": null, "agreed": null, "home_goals": null, "away_goals": null}}, {"model": "dashboard.game", "pk": 77, "fields": {"season": 1, "matchday": 6, "team_one": 1, "team_two": 4, "referee_team": null, "team_one_home_goals": null, "team_one_away_goals": null, "team_two_home_goals": null, "team_two_away_goals": null, "agreed": null, "home_goals": null, "away_goals": null}}, {"model": "dashboard.game", "pk": 78, "fields": {"season": 1, "matchday": 6, "team_one": 7, "team_two": 3, "referee_team": null, "team_one_home_goals": null, "team_one_away_goals": null, "team_two_home_goals": null, "team_two_away_goals": null, "agreed": null, "home_goals": null, "away_goals": null}}, {"model": "dashboard.game", "pk": 79, "fields": {"season": 1, "matchday": 6, "team_one": 6, "team_two": 8, "referee_team": null, "team_one_home_goals": null, "team_one_away_goals": null, "team_two_home_goals": null, "team_two_away_goals": null, "agreed": null, "home_goals": null, "away_goals": null}}, {"model": "dashboard.game", "pk": 80, "fields": {"season": 1, "matchday": 6, "team_one": 5, "team_two": 2, "referee_team": null, "team_one_home_goals": null, "team_one_away_goals": null, "team_two_home_goals": null, "team_two_away_goals": null, "agreed": null, "home_goals": null, "away_goals": null}}, {"model": "dashboard.game", "pk": 81, "fields": {"season": 1, "matchday": 7, "team_one": 4, "team_two": 7, "referee_team": null, "team_one_home_goals": null, "team_one_away_goals": null, "team_two_home_goals": null, "team_two_away_goals": null, "agreed": null, "home_goals": null, "away_goals": null}}, {"model": "dashboard.game", "pk": 82, "fields": {"season": 1, "matchday": 7, "team_one": 1, "team_two": 8, "referee_team": null, "team_one_home_goals": null, "team_one_away_goals": null, "team_two_home_goals": null, "team_two_away_goals": null, "agreed": null, "home_goals": null, "away_goals": null}}, {"model": "dashboard.game", "pk": 83, "fields": {"season": 1, "matchday": 7, "team_one": 2, "team_two": 3, "referee_team": null, "team_one_home_goals": null, "team_one_away_goals": null, "team_two_home_goals": null, "team_two_away_goals": null, "agreed": null, "home_goals": null, "away_goals": null}}, {"model": "dashboard.game", "pk": 84, "fields": {"season": 1, "matchday": 7, "team_one": 6, "team_two": 5, "referee_team": null, "team_one_home_goals": null, "team_one_away_goals": null, "team_two_home_goals": null, "team_two_away_goals": null, "agreed": null, "home_goals": null, "away_goals": null}}, {"model": "dashboard.teamrank", "pk": 1, "fields": {"matchday": 1, "team": 1, "refereed_games": 1, "wins": 0, "draws": 1, "losses": 0, "points": 1, "goals_scored": 2, "goals_conceded": 2}}, {"model": "dashboard.teamrank", "pk": 2, "fields": {"matchday": 1, "team": 2, "refereed_games": 0, "wins": 0, "draws": 0, "losses": 1, "points": 0, "goals_scored": 2, "goals_conceded": 12}}, {"model": "dashboard.teamrank", "pk": 3, "fields": {"matchday": 1, "team": 3, "refereed_games": 0, "wins": 0, "draws": 1, "losses": 0, "points": 1, "goals_scored": 2, "goals_conceded": 2}}, {"model": "dashboard.teamrank", "pk": 4, "fields": {"matchday": 1, "team": 4, "refereed_games": 0, "wins": 1, "draws": 0, "losses": 0, "points": 3, "goals_scored": 5, "goals_conceded": 3}}, {"model": "dashboard.teamrank", "pk": 5, "fields": {"matchday": 1, "team": 5, "refereed_games": 0, "wins": 0, "draws": 1, "losses": 0, "points": 1, "goals_scored": 2, "goals_conceded": 2}}, {"model": "dashboard.teamrank", "pk": 6, "fields": {"matchday": 1, "team": 6, "refereed_games": 0, "wins": 0, "draws": 1, "losses": 0, "points": 1, "goals_scored": 2, "goals_conceded": 2}}, {"model": "dashboard.teamrank", "pk": 7, "fields": {"matchday": 1, "team": 7, "refereed_games": 0, "wins": 1, "draws": 0, "losses": 0, "points": 3, "goals_scored": 12, "goals_conceded": 2}}, {"model": "dashboard.teamrank", "pk": 8, "fields": {"matchday": 1, "team": 8, "refereed_games": 0, "wins": 0, "draws": 0, "losses": 1, "points": 0, "goals_scored": 3, "goals_conceded": 5}}]